ARgorithmToolkit/__init__.py
ARgorithmToolkit/__main__.py
ARgorithmToolkit/array.py
ARgorithmToolkit/cli.py
ARgorithmToolkit/doublylinkedlist.py
ARgorithmToolkit/encoders.py
ARgorithmToolkit/linkedlist.py
ARgorithmToolkit/map.py
ARgorithmToolkit/parser.py
ARgorithmToolkit/priorityqueue.py
ARgorithmToolkit/queue.py
ARgorithmToolkit/security.py
ARgorithmToolkit/set.py
ARgorithmToolkit/stack.py
ARgorithmToolkit/string.py
ARgorithmToolkit/utils.py
ARgorithmToolkit/vector.py
ARgorithmToolkit/data/config.schema.json
ARgorithmToolkit/data/template.py
tests/__init__.py
tests/test_array.py
tests/test_base.py
tests/test_doublylinkedlist.py
tests/test_encoder.py
tests/test_linkedlist.py
tests/test_map.py
tests/test_priorityqueue.py
tests/test_queue.py
tests/test_set.py
tests/test_stack.py
tests/test_string.py
tests/test_vector.py
tests/utils.py
ARgorithmToolkit-0.2.3.dist-info/METADATA
ARgorithmToolkit-0.2.3.dist-info/WHEEL
ARgorithmToolkit-0.2.3.dist-info/entry_points.txt
ARgorithmToolkit-0.2.3.dist-info/top_level.txt
ARgorithmToolkit-0.2.3.dist-info/RECORD
