Metadata-Version: 2.1
Name: ARgorithmToolkit
Version: 0.2.3
Summary: A utility toolkit to help develop algorithms suitable for ARgorithm
Home-page: https://github.com/ARgorithm
Author: ARgorithm
Author-email: alansandra2013@gmail.com
License: UNKNOWN
Project-URL: Source, https://github.com/ARgorithm/toolkit
Project-URL: Bug Reports, https://github.com/ARgorithm/toolkit/issues
Project-URL: Documentation, https://argorithm.github.io/toolkit
Platform: UNKNOWN
Classifier: License :: OSI Approved :: MIT License
Classifier: Programming Language :: Python :: 3
Requires-Python: >=3.6
Requires-Dist: typer (>=0.3.2)
Requires-Dist: requests (>=2.25.1)
Requires-Dist: numpy (>=1.19.5)
Requires-Dist: halo (>=0.0.31)
Requires-Dist: jsonschema (>=3.2.0)
Requires-Dist: pyflakes (>=2.2.0)
